{"awayTeam":{"id":79,"logo":"https://r2.thesportsdb.com/images/media/team/badge/17eqox1688449282.png","name":"Toulouse"},"date":"15/03","generated_at":"2026-03-15T06:24:55.552903+00:00","homeTeam":{"id":93,"logo":"https://r2.thesportsdb.com/images/media/team/badge/1iuew61688452857.png","name":"Metz"},"id":1605,"insights":[{"id":"over25","probability":57,"title":"Over 2.5 provável"},{"id":"btts","probability":36,"title":"BTTS possível"},{"id":"cards","probability":4.800000000000001,"title":"Média de cartões"},{"id":"corners","probability":4.45,"title":"Escanteios por jogo"}],"league":"French Ligue 1","probabilities":{"away_win":33.13,"btts_yes":36.0,"draw":28.2,"home_win":38.53,"over_25":57.0},"team_rates":{"away":{"btts_yes":43,"over_25":57,"sample_size":5},"home":{"btts_yes":29,"over_25":57,"sample_size":5},"quality":"boa","sample_limit":5},"time":null}