[{"awayTeam":{"id":85,"logo":"https://r2.thesportsdb.com/images/media/team/badge/rwqrrq1473504808.png","name":"Paris SG"},"date":"06/05","date_iso":"2026-05-06","datetime_iso":"2026-05-06T00:00:00+00:00","homeTeam":{"id":50,"logo":"https://r2.thesportsdb.com/images/media/team/badge/01ogkh1716960412.png","name":"Bayern Munich"},"id":3177,"insights":[{"id":"over25","probability":64,"title":"Over 2.5 provável"},{"id":"btts","probability":43,"title":"BTTS possível"},{"id":"cards","probability":7.8999999999999995,"title":"Média de cartões"},{"id":"corners","probability":5.4,"title":"Escanteios por jogo"}],"league":"UEFA Champions League","time":"00:00"}]