{"awayTeam":{"id":117,"logo":"https://r2.thesportsdb.com/images/media/team/badge/o08wvi1635872307.png","name":"Charlton Athletic"},"date":"11/03","generated_at":"2026-03-10T06:16:56.950322+00:00","homeTeam":{"id":111,"logo":"https://r2.thesportsdb.com/images/media/team/badge/xxpttq1448811142.png","name":"Middlesbrough"},"id":2623,"insights":[{"id":"over25","probability":43,"title":"Over 2.5 provável"},{"id":"btts","probability":57,"title":"BTTS possível"},{"id":"cards","probability":7.5,"title":"Média de cartões"},{"id":"corners","probability":5.449999999999999,"title":"Escanteios por jogo"}],"league":"English League Championship","probabilities":{"away_win":33.13,"btts_yes":57.0,"draw":28.2,"home_win":38.53,"over_25":43.0},"team_rates":{"away":{"btts_yes":57,"over_25":43,"sample_size":5},"home":{"btts_yes":57,"over_25":43,"sample_size":5},"quality":"boa","sample_limit":5},"time":null}