[{"btts_yes":43.0,"match_id":2624,"over_25":50.0},{"btts_yes":64.0,"match_id":2625,"over_25":64.0},{"btts_yes":43.0,"match_id":2616,"over_25":57.0},{"btts_yes":57.0,"match_id":2615,"over_25":50.0},{"btts_yes":50.0,"match_id":2622,"over_25":50.0},{"btts_yes":57.0,"match_id":3047,"over_25":50.0},{"btts_yes":36.0,"match_id":3051,"over_25":43.0},{"btts_yes":50.0,"match_id":3057,"over_25":57.0},{"btts_yes":57.0,"match_id":3054,"over_25":43.0},{"btts_yes":57.0,"match_id":3058,"over_25":57.0},{"btts_yes":36.0,"match_id":3059,"over_25":43.0},{"btts_yes":0.0,"match_id":3060,"over_25":0.0},{"btts_yes":57.0,"match_id":2623,"over_25":43.0}]