[{"btts_yes":50.0,"match_id":2397,"over_25":50.0},{"btts_yes":43.0,"match_id":2314,"over_25":50.0},{"btts_yes":64.5,"match_id":2319,"over_25":50.0},{"btts_yes":71.5,"match_id":2324,"over_25":78.5},{"btts_yes":50.0,"match_id":2329,"over_25":50.0},{"btts_yes":50.0,"match_id":2334,"over_25":43.0},{"btts_yes":50.0,"match_id":2339,"over_25":57.0},{"btts_yes":42.5,"match_id":2344,"over_25":57.0},{"btts_yes":57.0,"match_id":2349,"over_25":57.0},{"btts_yes":64.0,"match_id":2357,"over_25":43.0},{"btts_yes":57.0,"match_id":2362,"over_25":50.0},{"btts_yes":57.0,"match_id":2367,"over_25":64.0},{"btts_yes":50.0,"match_id":2359,"over_25":57.0},{"btts_yes":43.0,"match_id":2372,"over_25":50.0},{"btts_yes":36.0,"match_id":2377,"over_25":36.0},{"btts_yes":57.0,"match_id":2382,"over_25":28.5},{"btts_yes":43.0,"match_id":2387,"over_25":50.0},{"btts_yes":43.0,"match_id":2392,"over_25":43.0},{"btts_yes":50.0,"match_id":2402,"over_25":43.0},{"btts_yes":50.0,"match_id":2354,"over_25":43.0}]