{"awayTeam":{"id":101,"logo":"https://r2.thesportsdb.com/images/media/team/badge/d16frn1678807158.png","name":"Stoke City"},"date":"06/04","generated_at":"2026-04-06T06:36:40.663640+00:00","homeTeam":{"id":110,"logo":"https://r2.thesportsdb.com/images/media/team/badge/jioo4z1557155744.png","name":"Derby County"},"id":2665,"insights":[{"id":"over25","probability":43,"title":"Over 2.5 provável"},{"id":"btts","probability":36,"title":"BTTS possível"},{"id":"cards","probability":12.8,"title":"Média de cartões"},{"id":"corners","probability":5.15,"title":"Escanteios por jogo"}],"league":"English League Championship","probabilities":{"away_win":33.13,"btts_yes":36.0,"draw":28.2,"home_win":38.53,"over_25":43.0},"team_rates":{"away":{"btts_yes":29,"over_25":43,"sample_size":5},"home":{"btts_yes":43,"over_25":43,"sample_size":5},"quality":"boa","sample_limit":5},"time":null}