{"best_by_market":{"away_win":{"bookmaker":"Betway","is_brazilian":true,"last_updated":"2026-03-20T06:20:05.213949+00:00","odd":4.2},"btts_no":null,"btts_yes":null,"draw":{"bookmaker":"Betway","is_brazilian":true,"last_updated":"2026-03-20T06:20:05.213949+00:00","odd":3.1},"home_win":{"bookmaker":"Betway","is_brazilian":true,"last_updated":"2026-03-20T06:20:05.213949+00:00","odd":2.0},"over_25":null,"under_25":null},"bookmakers":[{"bookmaker":"Betway","is_brazilian":true,"last_updated":"2026-03-20T06:20:05.213949+00:00","markets":{"away_win":4.2,"btts_no":null,"btts_yes":null,"draw":3.1,"home_win":2.0,"over_25":null,"under_25":null}}],"match":{"away":"Le Havre","date":"2026-03-22T00:00:00+00:00","home":"Paris FC","id":1668,"league":"French Ligue 1"}}